[
  {
    "price":1100,
    "title":"Apartamento T3 na Rua dos Lusíadas, Alto de Santo Amaro, Alcântara",
    "url":"https:\/\/www.idealista.pt\/imovel\/34788477\/",
    "location":"Rua dos Lusíadas, Alto de Santo Amaro, Alcântara",
    "area_m2":95,
    "typology":"T3",
    "source_file":"data\/lisboa_alcantara_listings.csv",
    "price_per_m2":11.5789473684,
    "furnished":false,
    "balcony":false,
    "terrace":false,
    "ac":false,
    "elevator":null,
    "parking":false,
    "kitchen_equipped":false,
    "renovated":false,
    "bills_included":false,
    "bathrooms":null,
    "bedrooms":null,
    "value_score":51.4210526316
  },
  {
    "price":1100,
    "title":"Apartamento T2 na Travessa das Dores, 19, Boa Hora, Ajuda",
    "url":"https:\/\/www.idealista.pt\/imovel\/34821294\/",
    "location":"Travessa das Dores, 19, Boa Hora, Ajuda",
    "area_m2":78,
    "typology":"T2",
    "source_file":"data\/lisboa_ajuda_listings.csv",
    "price_per_m2":14.1025641026,
    "furnished":false,
    "balcony":false,
    "terrace":false,
    "ac":false,
    "elevator":null,
    "parking":false,
    "kitchen_equipped":false,
    "renovated":false,
    "bills_included":false,
    "bathrooms":null,
    "bedrooms":null,
    "value_score":45.8974358974
  },
  {
    "price":1100,
    "title":"Apartamento T1 na Rua da Indústria, 33, Alto de Santo Amaro, Alcântara",
    "url":"https:\/\/www.idealista.pt\/imovel\/30445095\/",
    "location":"Rua da Indústria, 33, Alto de Santo Amaro, Alcântara",
    "area_m2":75,
    "typology":"T1",
    "source_file":"data\/lisboa_alcantara_listings.csv",
    "price_per_m2":14.6666666667,
    "furnished":false,
    "balcony":false,
    "terrace":false,
    "ac":false,
    "elevator":null,
    "parking":false,
    "kitchen_equipped":false,
    "renovated":false,
    "bills_included":false,
    "bathrooms":null,
    "bedrooms":null,
    "value_score":40.3333333333
  },
  {
    "price":950,
    "title":"Apartamento T1 na Rua Indústria, Alto de Santo Amaro, Alcântara",
    "url":"https:\/\/www.idealista.pt\/imovel\/30166333\/",
    "location":"Rua Indústria, Alto de Santo Amaro, Alcântara",
    "area_m2":60,
    "typology":"T1",
    "source_file":"data\/lisboa_alcantara_listings.csv",
    "price_per_m2":15.8333333333,
    "furnished":false,
    "balcony":false,
    "terrace":false,
    "ac":false,
    "elevator":null,
    "parking":false,
    "kitchen_equipped":false,
    "renovated":false,
    "bills_included":false,
    "bathrooms":null,
    "bedrooms":null,
    "value_score":39.1666666667
  },
  {
    "price":1150,
    "title":"Apartamento T1 em Junqueira, Alcântara",
    "url":"https:\/\/www.idealista.pt\/imovel\/34750866\/",
    "location":null,
    "area_m2":68,
    "typology":"T1",
    "source_file":"data\/lisboa_alcantara_listings.csv",
    "price_per_m2":16.9117647059,
    "furnished":false,
    "balcony":false,
    "terrace":false,
    "ac":false,
    "elevator":null,
    "parking":false,
    "kitchen_equipped":false,
    "renovated":false,
    "bills_included":false,
    "bathrooms":null,
    "bedrooms":null,
    "value_score":38.0882352941
  },
  {
    "price":900,
    "title":"Apartamento T1 em Boa Hora, Ajuda",
    "url":"https:\/\/www.idealista.pt\/imovel\/34555773\/",
    "location":null,
    "area_m2":50,
    "typology":"T1",
    "source_file":"data\/lisboa_ajuda_listings.csv",
    "price_per_m2":18.0,
    "furnished":false,
    "balcony":false,
    "terrace":false,
    "ac":false,
    "elevator":null,
    "parking":false,
    "kitchen_equipped":false,
    "renovated":false,
    "bills_included":false,
    "bathrooms":null,
    "bedrooms":null,
    "value_score":35.0
  },
  {
    "price":850,
    "title":"Apartamento T2 na Rua da Junqueira, 1, Junqueira, Alcântara",
    "url":"https:\/\/www.idealista.pt\/imovel\/34736072\/",
    "location":"Rua da Junqueira, 1, Junqueira, Alcântara",
    "area_m2":40,
    "typology":"T2",
    "source_file":"data\/lisboa_alcantara_listings.csv",
    "price_per_m2":21.25,
    "furnished":false,
    "balcony":false,
    "terrace":false,
    "ac":false,
    "elevator":null,
    "parking":false,
    "kitchen_equipped":false,
    "renovated":false,
    "bills_included":false,
    "bathrooms":null,
    "bedrooms":null,
    "value_score":34.75
  },
  {
    "price":995,
    "title":"Apartamento T1 na Rua José Osório de Oliveira, 8, Boa Hora, Ajuda",
    "url":"https:\/\/www.idealista.pt\/imovel\/29838642\/",
    "location":"Rua José Osório de Oliveira, 8, Boa Hora, Ajuda",
    "area_m2":50,
    "typology":"T1",
    "source_file":"data\/lisboa_ajuda_listings.csv",
    "price_per_m2":19.9,
    "furnished":false,
    "balcony":false,
    "terrace":false,
    "ac":false,
    "elevator":null,
    "parking":false,
    "kitchen_equipped":false,
    "renovated":false,
    "bills_included":false,
    "bathrooms":null,
    "bedrooms":null,
    "value_score":33.1
  },
  {
    "price":1100,
    "title":"Apartamento T1 em Alto de Santo Amaro, Alcântara",
    "url":"https:\/\/www.idealista.pt\/imovel\/34826169\/",
    "location":null,
    "area_m2":55,
    "typology":"T1",
    "source_file":"data\/lisboa_alcantara_listings.csv",
    "price_per_m2":20.0,
    "furnished":false,
    "balcony":false,
    "terrace":false,
    "ac":false,
    "elevator":null,
    "parking":false,
    "kitchen_equipped":false,
    "renovated":false,
    "bills_included":false,
    "bathrooms":null,
    "bedrooms":null,
    "value_score":33.0
  },
  {
    "price":1139,
    "title":"Apartamento T1 no Beco João Alves, 4, Rio Seco - Casalinho, Ajuda",
    "url":"https:\/\/www.idealista.pt\/imovel\/34774860\/",
    "location":null,
    "area_m2":55,
    "typology":"T1",
    "source_file":"data\/lisboa_ajuda_listings.csv",
    "price_per_m2":20.7090909091,
    "furnished":false,
    "balcony":false,
    "terrace":false,
    "ac":false,
    "elevator":null,
    "parking":false,
    "kitchen_equipped":false,
    "renovated":false,
    "bills_included":false,
    "bathrooms":null,
    "bedrooms":null,
    "value_score":32.2909090909
  },
  {
    "price":1173,
    "title":"Apartamento T1 no Beco João Alves, 4, Rio Seco - Casalinho, Ajuda",
    "url":"https:\/\/www.idealista.pt\/imovel\/34777785\/",
    "location":null,
    "area_m2":55,
    "typology":"T1",
    "source_file":"data\/lisboa_ajuda_listings.csv",
    "price_per_m2":21.3272727273,
    "furnished":false,
    "balcony":false,
    "terrace":false,
    "ac":false,
    "elevator":null,
    "parking":false,
    "kitchen_equipped":false,
    "renovated":false,
    "bills_included":false,
    "bathrooms":null,
    "bedrooms":null,
    "value_score":31.6727272727
  },
  {
    "price":1173,
    "title":"Apartamento T1 no Beco João Alves, 4, Rio Seco - Casalinho, Ajuda",
    "url":"https:\/\/www.idealista.pt\/imovel\/33113676\/",
    "location":null,
    "area_m2":55,
    "typology":"T1",
    "source_file":"data\/lisboa_ajuda_listings.csv",
    "price_per_m2":21.3272727273,
    "furnished":false,
    "balcony":false,
    "terrace":false,
    "ac":false,
    "elevator":null,
    "parking":false,
    "kitchen_equipped":false,
    "renovated":false,
    "bills_included":false,
    "bathrooms":null,
    "bedrooms":null,
    "value_score":31.6727272727
  },
  {
    "price":870,
    "title":"Apartamento T1 na Rua 1º de Maio, 69, Alto de Santo Amaro, Alcântara",
    "url":"https:\/\/www.idealista.pt\/imovel\/34824570\/",
    "location":"Rua 1º de Maio, 69, Alto de Santo Amaro, Alcântara",
    "area_m2":45,
    "typology":"T1",
    "source_file":"data\/lisboa_alcantara_listings.csv",
    "price_per_m2":19.3333333333,
    "furnished":false,
    "balcony":false,
    "terrace":false,
    "ac":false,
    "elevator":null,
    "parking":false,
    "kitchen_equipped":false,
    "renovated":false,
    "bills_included":false,
    "bathrooms":null,
    "bedrooms":null,
    "value_score":31.6666666667
  },
  {
    "price":950,
    "title":"Apartamento T1 na Travessa São Jerónimo, 2, Alvito - Quinta do Jacinto, Alcântara",
    "url":"https:\/\/www.idealista.pt\/imovel\/31161260\/",
    "location":"Travessa São Jerónimo, 2, Alvito - Quinta do Jacinto, Alcântara",
    "area_m2":45,
    "typology":"T1",
    "source_file":"data\/lisboa_alcantara_listings.csv",
    "price_per_m2":21.1111111111,
    "furnished":false,
    "balcony":false,
    "terrace":false,
    "ac":false,
    "elevator":null,
    "parking":false,
    "kitchen_equipped":false,
    "renovated":false,
    "bills_included":false,
    "bathrooms":null,
    "bedrooms":null,
    "value_score":29.8888888889
  },
  {
    "price":1100,
    "title":"Apartamento T2 na Rua Cruz a Alcântara, 36, Alvito - Quinta do Jacinto, Alcântara",
    "url":"https:\/\/www.idealista.pt\/imovel\/33157926\/",
    "location":"Rua Cruz a Alcântara, 36, Alvito - Quinta do Jacinto, Alcântara",
    "area_m2":42,
    "typology":"T2",
    "source_file":"data\/lisboa_alcantara_listings.csv",
    "price_per_m2":26.1904761905,
    "furnished":false,
    "balcony":false,
    "terrace":false,
    "ac":false,
    "elevator":null,
    "parking":false,
    "kitchen_equipped":false,
    "renovated":false,
    "bills_included":false,
    "bathrooms":null,
    "bedrooms":null,
    "value_score":29.8095238095
  },
  {
    "price":850,
    "title":"Apartamento T0 no Beco João Alves, 3, Rio Seco - Casalinho, Ajuda",
    "url":"https:\/\/www.idealista.pt\/imovel\/34812075\/",
    "location":null,
    "area_m2":40,
    "typology":"T0",
    "source_file":"data\/lisboa_ajuda_listings.csv",
    "price_per_m2":21.25,
    "furnished":false,
    "balcony":false,
    "terrace":false,
    "ac":false,
    "elevator":null,
    "parking":false,
    "kitchen_equipped":false,
    "renovated":false,
    "bills_included":false,
    "bathrooms":null,
    "bedrooms":null,
    "value_score":29.75
  },
  {
    "price":850,
    "title":"Apartamento T0 no Beco João Alves, 3, Rio Seco - Casalinho, Ajuda",
    "url":"https:\/\/www.idealista.pt\/imovel\/33110276\/",
    "location":null,
    "area_m2":40,
    "typology":"T0",
    "source_file":"data\/lisboa_ajuda_listings.csv",
    "price_per_m2":21.25,
    "furnished":false,
    "balcony":false,
    "terrace":false,
    "ac":false,
    "elevator":null,
    "parking":false,
    "kitchen_equipped":false,
    "renovated":false,
    "bills_included":false,
    "bathrooms":null,
    "bedrooms":null,
    "value_score":29.75
  },
  {
    "price":850,
    "title":"Apartamento T0 no Beco João Alves, 3, Rio Seco - Casalinho, Ajuda",
    "url":"https:\/\/www.idealista.pt\/imovel\/33110275\/",
    "location":null,
    "area_m2":40,
    "typology":"T0",
    "source_file":"data\/lisboa_ajuda_listings.csv",
    "price_per_m2":21.25,
    "furnished":false,
    "balcony":false,
    "terrace":false,
    "ac":false,
    "elevator":null,
    "parking":false,
    "kitchen_equipped":false,
    "renovated":false,
    "bills_included":false,
    "bathrooms":null,
    "bedrooms":null,
    "value_score":29.75
  },
  {
    "price":850,
    "title":"Apartamento T0 no Beco João Alves, 3, Rio Seco - Casalinho, Ajuda",
    "url":"https:\/\/www.idealista.pt\/imovel\/34814425\/",
    "location":null,
    "area_m2":40,
    "typology":"T0",
    "source_file":"data\/lisboa_ajuda_listings.csv",
    "price_per_m2":21.25,
    "furnished":false,
    "balcony":false,
    "terrace":false,
    "ac":false,
    "elevator":null,
    "parking":false,
    "kitchen_equipped":false,
    "renovated":false,
    "bills_included":false,
    "bathrooms":null,
    "bedrooms":null,
    "value_score":29.75
  },
  {
    "price":955,
    "title":"Apartamento T0 na Travessa de São Jerónimo, 2, Alvito - Quinta do Jacinto, Alcântara",
    "url":"https:\/\/www.idealista.pt\/imovel\/34824242\/",
    "location":"Travessa de São Jerónimo, 2, Alvito - Quinta do Jacinto, Alcântara",
    "area_m2":44,
    "typology":"T0",
    "source_file":"data\/lisboa_alcantara_listings.csv",
    "price_per_m2":21.7045454545,
    "furnished":false,
    "balcony":false,
    "terrace":false,
    "ac":false,
    "elevator":null,
    "parking":false,
    "kitchen_equipped":false,
    "renovated":false,
    "bills_included":false,
    "bathrooms":null,
    "bedrooms":null,
    "value_score":29.2954545455
  },
  {
    "price":870,
    "title":"Apartamento T0 na Rua Giovanni Antinori, 4, Rio Seco - Casalinho, Ajuda",
    "url":"https:\/\/www.idealista.pt\/imovel\/34284629\/",
    "location":"Rua Giovanni Antinori, 4, Rio Seco - Casalinho, Ajuda",
    "area_m2":40,
    "typology":"T0",
    "source_file":"data\/lisboa_ajuda_listings.csv",
    "price_per_m2":21.75,
    "furnished":false,
    "balcony":false,
    "terrace":false,
    "ac":false,
    "elevator":null,
    "parking":false,
    "kitchen_equipped":false,
    "renovated":false,
    "bills_included":false,
    "bathrooms":null,
    "bedrooms":null,
    "value_score":29.25
  },
  {
    "price":870,
    "title":"Apartamento T0 no Beco João Alves, 3, Rio Seco - Casalinho, Ajuda",
    "url":"https:\/\/www.idealista.pt\/imovel\/34809700\/",
    "location":null,
    "area_m2":40,
    "typology":"T0",
    "source_file":"data\/lisboa_ajuda_listings.csv",
    "price_per_m2":21.75,
    "furnished":false,
    "balcony":false,
    "terrace":false,
    "ac":false,
    "elevator":null,
    "parking":false,
    "kitchen_equipped":false,
    "renovated":false,
    "bills_included":false,
    "bathrooms":null,
    "bedrooms":null,
    "value_score":29.25
  },
  {
    "price":915,
    "title":"Apartamento T0 no Beco João Alves, 3, Rio Seco - Casalinho, Ajuda",
    "url":"https:\/\/www.idealista.pt\/imovel\/33110278\/",
    "location":null,
    "area_m2":40,
    "typology":"T0",
    "source_file":"data\/lisboa_ajuda_listings.csv",
    "price_per_m2":22.875,
    "furnished":false,
    "balcony":false,
    "terrace":false,
    "ac":false,
    "elevator":null,
    "parking":false,
    "kitchen_equipped":false,
    "renovated":false,
    "bills_included":false,
    "bathrooms":null,
    "bedrooms":null,
    "value_score":28.125
  },
  {
    "price":915,
    "title":"Apartamento T0 no Beco João Alves, 3, Rio Seco - Casalinho, Ajuda",
    "url":"https:\/\/www.idealista.pt\/imovel\/34803526\/",
    "location":null,
    "area_m2":40,
    "typology":"T0",
    "source_file":"data\/lisboa_ajuda_listings.csv",
    "price_per_m2":22.875,
    "furnished":false,
    "balcony":false,
    "terrace":false,
    "ac":false,
    "elevator":null,
    "parking":false,
    "kitchen_equipped":false,
    "renovated":false,
    "bills_included":false,
    "bathrooms":null,
    "bedrooms":null,
    "value_score":28.125
  },
  {
    "price":800,
    "title":"Apartamento T1 em Rio Seco - Casalinho, Ajuda",
    "url":"https:\/\/www.idealista.pt\/imovel\/34727469\/",
    "location":null,
    "area_m2":35,
    "typology":"T1",
    "source_file":"data\/lisboa_ajuda_listings.csv",
    "price_per_m2":22.8571428571,
    "furnished":false,
    "balcony":false,
    "terrace":false,
    "ac":false,
    "elevator":null,
    "parking":false,
    "kitchen_equipped":false,
    "renovated":false,
    "bills_included":false,
    "bathrooms":null,
    "bedrooms":null,
    "value_score":27.1428571429
  },
  {
    "price":970,
    "title":"Apartamento T0 no Beco João Alves, 2, Rio Seco - Casalinho, Ajuda",
    "url":"https:\/\/www.idealista.pt\/imovel\/33110273\/",
    "location":null,
    "area_m2":40,
    "typology":"T0",
    "source_file":"data\/lisboa_ajuda_listings.csv",
    "price_per_m2":24.25,
    "furnished":false,
    "balcony":false,
    "terrace":false,
    "ac":false,
    "elevator":null,
    "parking":false,
    "kitchen_equipped":false,
    "renovated":false,
    "bills_included":false,
    "bathrooms":null,
    "bedrooms":null,
    "value_score":26.75
  },
  {
    "price":970,
    "title":"Apartamento T0 no Beco João Alves, 2, Rio Seco - Casalinho, Ajuda",
    "url":"https:\/\/www.idealista.pt\/imovel\/34817020\/",
    "location":null,
    "area_m2":40,
    "typology":"T0",
    "source_file":"data\/lisboa_ajuda_listings.csv",
    "price_per_m2":24.25,
    "furnished":false,
    "balcony":false,
    "terrace":false,
    "ac":false,
    "elevator":null,
    "parking":false,
    "kitchen_equipped":false,
    "renovated":false,
    "bills_included":false,
    "bathrooms":null,
    "bedrooms":null,
    "value_score":26.75
  },
  {
    "price":1093,
    "title":"Apartamento T1 no Beco João Alves, Rio Seco - Casalinho, Ajuda",
    "url":"https:\/\/www.idealista.pt\/imovel\/34777389\/",
    "location":null,
    "area_m2":44,
    "typology":"T1",
    "source_file":"data\/lisboa_ajuda_listings.csv",
    "price_per_m2":24.8409090909,
    "furnished":false,
    "balcony":false,
    "terrace":false,
    "ac":false,
    "elevator":null,
    "parking":false,
    "kitchen_equipped":false,
    "renovated":false,
    "bills_included":false,
    "bathrooms":null,
    "bedrooms":null,
    "value_score":26.1590909091
  },
  {
    "price":1100,
    "title":"Apartamento T1 na Travessa do Gibraltar, Alvito - Quinta do Jacinto, Alcântara",
    "url":"https:\/\/www.idealista.pt\/imovel\/34766697\/",
    "location":"Travessa do Gibraltar, Alvito - Quinta do Jacinto, Alcântara",
    "area_m2":44,
    "typology":"T1",
    "source_file":"data\/lisboa_alcantara_listings.csv",
    "price_per_m2":25.0,
    "furnished":false,
    "balcony":false,
    "terrace":false,
    "ac":false,
    "elevator":null,
    "parking":false,
    "kitchen_equipped":false,
    "renovated":false,
    "bills_included":false,
    "bathrooms":null,
    "bedrooms":null,
    "value_score":26.0
  },
  {
    "price":1001,
    "title":"Apartamento T0 no Beco João Alves, 3, Rio Seco - Casalinho, Ajuda",
    "url":"https:\/\/www.idealista.pt\/imovel\/33404488\/",
    "location":null,
    "area_m2":40,
    "typology":"T0",
    "source_file":"data\/lisboa_ajuda_listings.csv",
    "price_per_m2":25.025,
    "furnished":false,
    "balcony":false,
    "terrace":false,
    "ac":false,
    "elevator":null,
    "parking":false,
    "kitchen_equipped":false,
    "renovated":false,
    "bills_included":false,
    "bathrooms":null,
    "bedrooms":null,
    "value_score":25.975
  },
  {
    "price":1001,
    "title":"Apartamento T0 no Beco João Alves, 3, Rio Seco - Casalinho, Ajuda",
    "url":"https:\/\/www.idealista.pt\/imovel\/34806989\/",
    "location":null,
    "area_m2":40,
    "typology":"T0",
    "source_file":"data\/lisboa_ajuda_listings.csv",
    "price_per_m2":25.025,
    "furnished":false,
    "balcony":false,
    "terrace":false,
    "ac":false,
    "elevator":null,
    "parking":false,
    "kitchen_equipped":false,
    "renovated":false,
    "bills_included":false,
    "bathrooms":null,
    "bedrooms":null,
    "value_score":25.975
  },
  {
    "price":1180,
    "title":"Apartamento T1 no Largo do Calvário, Largo do Calvário - Lx Factory, Alcântara",
    "url":"https:\/\/www.idealista.pt\/imovel\/34602502\/",
    "location":null,
    "area_m2":47,
    "typology":"T1",
    "source_file":"data\/lisboa_alcantara_listings.csv",
    "price_per_m2":25.1063829787,
    "furnished":false,
    "balcony":false,
    "terrace":false,
    "ac":false,
    "elevator":null,
    "parking":false,
    "kitchen_equipped":false,
    "renovated":false,
    "bills_included":false,
    "bathrooms":null,
    "bedrooms":null,
    "value_score":25.8936170213
  },
  {
    "price":1093,
    "title":"Apartamento T1 no Beco João Alves, Rio Seco - Casalinho, Ajuda",
    "url":"https:\/\/www.idealista.pt\/imovel\/34792036\/",
    "location":null,
    "area_m2":42,
    "typology":"T1",
    "source_file":"data\/lisboa_ajuda_listings.csv",
    "price_per_m2":26.0238095238,
    "furnished":false,
    "balcony":false,
    "terrace":false,
    "ac":false,
    "elevator":null,
    "parking":false,
    "kitchen_equipped":false,
    "renovated":false,
    "bills_included":false,
    "bathrooms":null,
    "bedrooms":null,
    "value_score":24.9761904762
  },
  {
    "price":1075,
    "title":"Apartamento T0 na Travessa Artur Lamas, s\/n, Junqueira, Alcântara",
    "url":"https:\/\/www.idealista.pt\/imovel\/34780316\/",
    "location":"Travessa Artur Lamas, s\/n, Junqueira, Alcântara",
    "area_m2":40,
    "typology":"T0",
    "source_file":"data\/lisboa_alcantara_listings.csv",
    "price_per_m2":26.875,
    "furnished":false,
    "balcony":false,
    "terrace":false,
    "ac":false,
    "elevator":null,
    "parking":false,
    "kitchen_equipped":false,
    "renovated":false,
    "bills_included":false,
    "bathrooms":null,
    "bedrooms":null,
    "value_score":24.125
  },
  {
    "price":1100,
    "title":"Apartamento T0 na Travessa da Memória, 18, Calçada da Ajuda - Belém, Ajuda",
    "url":"https:\/\/www.idealista.pt\/imovel\/34579935\/",
    "location":"Travessa da Memória, 18, Calçada da Ajuda - Belém, Ajuda",
    "area_m2":40,
    "typology":"T0",
    "source_file":"data\/lisboa_ajuda_listings.csv",
    "price_per_m2":27.5,
    "furnished":false,
    "balcony":false,
    "terrace":false,
    "ac":false,
    "elevator":null,
    "parking":false,
    "kitchen_equipped":false,
    "renovated":false,
    "bills_included":false,
    "bathrooms":null,
    "bedrooms":null,
    "value_score":23.5
  },
  {
    "price":1125,
    "title":"Apartamento T0 na Travessa Artur Lamas, s\/n, Junqueira, Alcântara",
    "url":"https:\/\/www.idealista.pt\/imovel\/34794468\/",
    "location":"Travessa Artur Lamas, s\/n, Junqueira, Alcântara",
    "area_m2":40,
    "typology":"T0",
    "source_file":"data\/lisboa_alcantara_listings.csv",
    "price_per_m2":28.125,
    "furnished":false,
    "balcony":false,
    "terrace":false,
    "ac":false,
    "elevator":null,
    "parking":false,
    "kitchen_equipped":false,
    "renovated":false,
    "bills_included":false,
    "bathrooms":null,
    "bedrooms":null,
    "value_score":22.875
  },
  {
    "price":1125,
    "title":"Apartamento T0 na Travessa Artur Lamas, s\/n, Junqueira, Alcântara",
    "url":"https:\/\/www.idealista.pt\/imovel\/34616472\/",
    "location":"Travessa Artur Lamas, s\/n, Junqueira, Alcântara",
    "area_m2":40,
    "typology":"T0",
    "source_file":"data\/lisboa_alcantara_listings.csv",
    "price_per_m2":28.125,
    "furnished":false,
    "balcony":false,
    "terrace":false,
    "ac":false,
    "elevator":null,
    "parking":false,
    "kitchen_equipped":false,
    "renovated":false,
    "bills_included":false,
    "bathrooms":null,
    "bedrooms":null,
    "value_score":22.875
  },
  {
    "price":1000,
    "title":"Apartamento T1 na Rua Rodrigues de Faria, 107, Largo do Calvário - Lx Factory, Alcântara",
    "url":"https:\/\/www.idealista.pt\/imovel\/34814868\/",
    "location":"Rua Rodrigues de Faria, 107, Largo do Calvário - Lx Factory, Alcântara",
    "area_m2":35,
    "typology":"T1",
    "source_file":"data\/lisboa_alcantara_listings.csv",
    "price_per_m2":28.5714285714,
    "furnished":false,
    "balcony":false,
    "terrace":false,
    "ac":false,
    "elevator":null,
    "parking":false,
    "kitchen_equipped":false,
    "renovated":false,
    "bills_included":false,
    "bathrooms":null,
    "bedrooms":null,
    "value_score":21.4285714286
  },
  {
    "price":750,
    "title":"Apartamento T0 na Rua das Chaminés D'El-Rei, 39, Caramão da Ajuda, Ajuda",
    "url":"https:\/\/www.idealista.pt\/imovel\/34575941\/",
    "location":"Rua das Chaminés D'El-Rei, 39, Caramão da Ajuda, Ajuda",
    "area_m2":25,
    "typology":"T0",
    "source_file":"data\/lisboa_ajuda_listings.csv",
    "price_per_m2":30.0,
    "furnished":false,
    "balcony":false,
    "terrace":false,
    "ac":false,
    "elevator":null,
    "parking":false,
    "kitchen_equipped":false,
    "renovated":false,
    "bills_included":false,
    "bathrooms":null,
    "bedrooms":null,
    "value_score":20.0
  },
  {
    "price":919,
    "title":"Apartamento T0 no Largo do Calvário, Largo do Calvário - Lx Factory, Alcântara",
    "url":"https:\/\/www.idealista.pt\/imovel\/34404843\/",
    "location":null,
    "area_m2":30,
    "typology":"T0",
    "source_file":"data\/lisboa_alcantara_listings.csv",
    "price_per_m2":30.6333333333,
    "furnished":false,
    "balcony":false,
    "terrace":false,
    "ac":false,
    "elevator":null,
    "parking":false,
    "kitchen_equipped":false,
    "renovated":false,
    "bills_included":false,
    "bathrooms":null,
    "bedrooms":null,
    "value_score":19.3666666667
  },
  {
    "price":800,
    "title":"Apartamento T0 na Rua Amadeu de Sousa Cardoso, s\/n, Alto de Santo Amaro, Alcântara",
    "url":"https:\/\/www.idealista.pt\/imovel\/34822424\/",
    "location":"Rua Amadeu de Sousa Cardoso, s\/n, Alto de Santo Amaro, Alcântara",
    "area_m2":25,
    "typology":"T0",
    "source_file":"data\/lisboa_alcantara_listings.csv",
    "price_per_m2":32.0,
    "furnished":false,
    "balcony":false,
    "terrace":false,
    "ac":false,
    "elevator":null,
    "parking":false,
    "kitchen_equipped":false,
    "renovated":false,
    "bills_included":false,
    "bathrooms":null,
    "bedrooms":null,
    "value_score":18.0
  },
  {
    "price":998,
    "title":"Apartamento T0 no Largo do Calvário, Largo do Calvário - Lx Factory, Alcântara",
    "url":"https:\/\/www.idealista.pt\/imovel\/34404788\/",
    "location":null,
    "area_m2":30,
    "typology":"T0",
    "source_file":"data\/lisboa_alcantara_listings.csv",
    "price_per_m2":33.2666666667,
    "furnished":false,
    "balcony":false,
    "terrace":false,
    "ac":false,
    "elevator":null,
    "parking":false,
    "kitchen_equipped":false,
    "renovated":false,
    "bills_included":false,
    "bathrooms":null,
    "bedrooms":null,
    "value_score":16.7333333333
  },
  {
    "price":850,
    "title":"Apartamento T0 na Rua do cruzeiro, 199, Rio Seco - Casalinho, Ajuda",
    "url":"https:\/\/www.idealista.pt\/imovel\/32853662\/",
    "location":"Rua do cruzeiro, 199, Rio Seco - Casalinho, Ajuda",
    "area_m2":25,
    "typology":"T0",
    "source_file":"data\/lisboa_ajuda_listings.csv",
    "price_per_m2":34.0,
    "furnished":false,
    "balcony":false,
    "terrace":false,
    "ac":false,
    "elevator":null,
    "parking":false,
    "kitchen_equipped":false,
    "renovated":false,
    "bills_included":false,
    "bathrooms":null,
    "bedrooms":null,
    "value_score":16.0
  },
  {
    "price":950,
    "title":"Apartamento T0 na Rua Giovanni Antinori, 1, Rio Seco - Casalinho, Ajuda",
    "url":"https:\/\/www.idealista.pt\/imovel\/30786570\/",
    "location":"Rua Giovanni Antinori, 1, Rio Seco - Casalinho, Ajuda",
    "area_m2":25,
    "typology":"T0",
    "source_file":"data\/lisboa_ajuda_listings.csv",
    "price_per_m2":38.0,
    "furnished":false,
    "balcony":false,
    "terrace":false,
    "ac":false,
    "elevator":null,
    "parking":false,
    "kitchen_equipped":false,
    "renovated":false,
    "bills_included":false,
    "bathrooms":null,
    "bedrooms":null,
    "value_score":12.0
  },
  {
    "price":1035,
    "title":"Apartamento T0 na Rua Aliança Operária, 2, Alto de Alcântara, Alcântara",
    "url":"https:\/\/www.idealista.pt\/imovel\/34809532\/",
    "location":"Rua Aliança Operária, 2, Alto de Alcântara, Alcântara",
    "area_m2":24,
    "typology":"T0",
    "source_file":"data\/lisboa_alcantara_listings.csv",
    "price_per_m2":43.125,
    "furnished":false,
    "balcony":false,
    "terrace":false,
    "ac":false,
    "elevator":null,
    "parking":false,
    "kitchen_equipped":false,
    "renovated":false,
    "bills_included":false,
    "bathrooms":null,
    "bedrooms":null,
    "value_score":6.875
  },
  {
    "price":660,
    "title":"Apartamento T0 no Bairro do Alvito, 47, Alvito - Quinta do Jacinto, Alcântara",
    "url":"https:\/\/www.idealista.pt\/imovel\/31376270\/",
    "location":null,
    "area_m2":15,
    "typology":"T0",
    "source_file":"data\/lisboa_alcantara_listings.csv",
    "price_per_m2":44.0,
    "furnished":false,
    "balcony":false,
    "terrace":false,
    "ac":false,
    "elevator":null,
    "parking":false,
    "kitchen_equipped":false,
    "renovated":false,
    "bills_included":false,
    "bathrooms":null,
    "bedrooms":null,
    "value_score":6.0
  },
  {
    "price":1173,
    "title":"Apartamento T0 no Beco João Alves, Rio Seco - Casalinho, Ajuda",
    "url":"https:\/\/www.idealista.pt\/imovel\/34806511\/",
    "location":null,
    "area_m2":24,
    "typology":"T0",
    "source_file":"data\/lisboa_ajuda_listings.csv",
    "price_per_m2":48.875,
    "furnished":false,
    "balcony":false,
    "terrace":false,
    "ac":false,
    "elevator":null,
    "parking":false,
    "kitchen_equipped":false,
    "renovated":false,
    "bills_included":false,
    "bathrooms":null,
    "bedrooms":null,
    "value_score":1.125
  },
  {
    "price":760,
    "title":"Apartamento T0,  R. Aliança Operária, 2, Alto de Alcântara, Alcântara",
    "url":"https:\/\/www.idealista.pt\/imovel\/33115927\/",
    "location":null,
    "area_m2":11,
    "typology":"T0",
    "source_file":"data\/lisboa_alcantara_listings.csv",
    "price_per_m2":69.0909090909,
    "furnished":false,
    "balcony":false,
    "terrace":false,
    "ac":false,
    "elevator":null,
    "parking":false,
    "kitchen_equipped":false,
    "renovated":false,
    "bills_included":false,
    "bathrooms":null,
    "bedrooms":null,
    "value_score":0.0
  },
  {
    "price":870,
    "title":"Apartamento T0 no Beco João Alves, Rio Seco - Casalinho, Ajuda",
    "url":"https:\/\/www.idealista.pt\/imovel\/34746289\/",
    "location":null,
    "area_m2":10,
    "typology":"T0",
    "source_file":"data\/lisboa_ajuda_listings.csv",
    "price_per_m2":87.0,
    "furnished":false,
    "balcony":false,
    "terrace":false,
    "ac":false,
    "elevator":null,
    "parking":false,
    "kitchen_equipped":false,
    "renovated":false,
    "bills_included":false,
    "bathrooms":null,
    "bedrooms":null,
    "value_score":0.0
  }
]